README.rst
setup.cfg
setup.py
bin/hubsync
hubsync/__init__.py
hubsync/config.py
hubsync/github.py
hubsync/sync.py
hubsync/workspace.py
hubsync.egg-info/PKG-INFO
hubsync.egg-info/SOURCES.txt
hubsync.egg-info/dependency_links.txt
hubsync.egg-info/requires.txt
hubsync.egg-info/top_level.txt