Metadata-Version: 1.0
Name: hubsync
Version: 0.1.8
Summary: Get your github workspace synced!
Home-page: https://github.com/Mariocj89/hubsync
Author: Mario Corchero
Author-email: mariocj89@gmail.com
License: UNKNOWN
Keywords: github,sync,workspace
Platform: UNKNOWN
